drf_firebase3_auth/__init__.py
drf_firebase3_auth/admin.py
drf_firebase3_auth/apps.py
drf_firebase3_auth/authentication.py
drf_firebase3_auth/models.py
drf_firebase3_auth/settings.py
drf_firebase3_auth/migrations/0001_initial.py
drf_firebase3_auth/migrations/__init__.py
drf_firebase3_auth-0.0.7.dist-info/METADATA
drf_firebase3_auth-0.0.7.dist-info/WHEEL
drf_firebase3_auth-0.0.7.dist-info/top_level.txt
drf_firebase3_auth-0.0.7.dist-info/RECORD
