Metadata-Version: 2.1
Name: drf-firebase3-auth
Version: 0.0.7
Summary: Custom Django Rest Framework authentication backend for parsing Firebase uid tokens and storing as local users.
Home-page: https://github.com/p141592/drf-firebase-auth
Author: Baryshnikov Nikolay
Author-email: mr.boiled@gmail.com
License: MIT
Platform: UNKNOWN
Classifier: Development Status :: 5 - Production/Stable
Classifier: Environment :: Web Environment
Classifier: Framework :: Django
Classifier: Intended Audience :: Developers
Classifier: License :: OSI Approved :: MIT License
Classifier: Operating System :: OS Independent
Classifier: Programming Language :: Python
Classifier: Programming Language :: Python :: 3
Classifier: Programming Language :: Python :: 3.3
Classifier: Programming Language :: Python :: 3.4
Classifier: Programming Language :: Python :: 3.5
Classifier: Programming Language :: Python :: 3.6
Classifier: Topic :: Internet :: WWW/HTTP
Requires-Dist: firebase-admin (>=3.0.0)
